versionio/__init__.py
versionio/core.py
versionio/exceptions.py
versionio/policy.py
versionio/py.typed
versionio/utils.py
versionio/version.py
versionio/wrapper.py
versionio-0.1.1.dist-info/licenses/LICENSE
versionio-0.1.1.dist-info/METADATA
versionio-0.1.1.dist-info/WHEEL
versionio-0.1.1.dist-info/top_level.txt
versionio-0.1.1.dist-info/RECORD
