Metadata-Version: 2.4
Name: versionio
Version: 0.1.1
Summary: Drop-in replacement for open() with automatic file versioning
Author-email: Nikhil Shekhawat <nikhilshekhawat1999@gmail.com>
License: MIT
Requires-Python: >=3.8
License-File: LICENSE
Provides-Extra: dev
Requires-Dist: pytest>=7.0; extra == "dev"
Requires-Dist: pytest-cov>=4.0; extra == "dev"
Dynamic: license-file
